{
  "RANK_CARD_ORDER": [
    "A",
    "2",
    "3",
    "4",
    "5",
    "6",
    "7",
    "8",
    "9",
    "10",
    "J",
    "Q",
    "K"
  ],
  "SUITS": [
    "♥",
    "♦",
    "♠",
    "♣"
  ],
  "JOKER_SUIT": "🃏",
  "MIN_PACK_IN_DECK": 2,
  "COUNT_OF_PLAYERS_FOR_EXTRA_PACK": 5,
  "PLAYERS_PER_EXTRA_PACK": 3,
  "JOKER": "Jr",
  "EMPTY_BUS_STOP": [
    [],
    [],
    [],
    []
  ],
  "Roles": {
    "ADMIN": "admin",
    "VIP": "vip",
    "PLEB": "pleb",
    "ALL": [
      "admin",
      "vip",
      "pleb"
    ]
  },
  "States": {
    "INITIAL": "initial",
    "ACTIVE": "active",
    "FINISHED": "finished",
    "CLOSED": "closed"
  },
  "MinNumberOfPlayers": {
    "NON_ACTIVE": 1,
    "ACTIVE": 2
  },
  "Bg": {
    "RED": "red",
    "BLUE": "blue"
  },
  "MAX_ATTEMPTS": 5,
  "CREATOR": "creator",
  "DEFAULT_NAME": "nemo",
  "SlotTargets": {
    "HAND": "hand",
    "BUS": "bus_",
    "EMPTY_HAND": "empty_hand_",
    "PLAYER": "player_",
    "PLAYER_BUS": "player_bus_",
    "PLAYER_SLOT": "player_slot_",
    "MYSELF": "myself_",
    "CARDPACK_DECK": "cardpack_deck",
    "COMPLETED_CARDPACK_DECK": "completed_cardpack_deck",
    "GAMEBOARD_CARD": "gb_card_",
    "GAMEBOARD_NO_CARD": "gb_nocard_"
  },
  "MIN_ZOOM": 0.5,
  "MAX_ZOOM": 1.25,
  "ZOOM_STEP": 0.1
}